{
  "id": "data-card-25",
  "labels": [
    "Item"
  ],
  "data": {
    "cost": 0,
    "name": "Data Card 25",
    "summary": "Records the number of times the trainer's Pokémon received prizes in the Pokéathlon.",
    "description": "Records the number of times the trainer's Pokémon received prizes in the Pokéathlon."
  },
  "locale": {
    "ja": {
      "name": "データカード２５"
    },
    "ko": {
      "name": "데이터카드25"
    },
    "fr": {
      "name": "Carte Mémo25"
    },
    "de": {
      "name": "Datenkarte25"
    },
    "es": {
      "name": "Tarjeta Datos 25"
    },
    "it": {
      "name": "Scheda Dati 25"
    }
  }
}