{
  "id": "growth-mulch",
  "labels": [
    "Item"
  ],
  "data": {
    "cost": 200,
    "name": "Growth Mulch",
    "summary": "Growing time of berries is reduced, but the soil dries out faster.",
    "description": "Used on a patch of soil\n:   Plant's growth stages will each last 25% less time.  Dries soil out more quickly."
  },
  "locale": {
    "ja": {
      "name": "すくすくこやし"
    },
    "ko": {
      "name": "무럭무럭비료"
    },
    "fr": {
      "name": "Fertipousse"
    },
    "de": {
      "name": "Wachsmulch"
    },
    "es": {
      "name": "Abono Rápido"
    },
    "it": {
      "name": "Fertilrapido"
    }
  }
}