{
  "id": "hunter-dilus",
  "labels": [
    "Enemy"
  ],
  "data": {
    "name": "Hunter Dilus",
    "type": "normal",
    "subcategory": "Dilus",
    "category": "Theroid",
    "level_range": {
      "minimum": 51,
      "maximum": 60
    },
    "experience_range": {
      "minimum": 594,
      "maximum": 764
    },
    "health_range": {
      "minimum": 105799,
      "maximum": 123809
    },
    "melee_power_range": {
      "minimum": 1184,
      "maximum": 1476
    },
    "melee_accuracy_range": {
      "minimum": 268,
      "maximum": 308
    },
    "ranged_power_range": {
      "minimum": 937,
      "maximum": 1168
    },
    "ranged_accuracy_range": {
      "minimum": 233,
      "maximum": 268
    },
    "potential_range": {
      "minimum": 888,
      "maximum": 1107
    },
    "evasion_range": {
      "minimum": 138,
      "maximum": 171
    },
    "notes": "Found at 207NW",
    "time": "TBD",
    "weather": "TBD",
    "physical_resistance": 0,
    "beam_resistance": 0,
    "ether_resistance": -25,
    "thermal_resistance": -50,
    "electric_resistance": 0,
    "gravity_resistance": 0
  }
}
