{
  "id": "sand-aeviter",
  "labels": [
    "Enemy"
  ],
  "data": {
    "name": "Sand Aeviter",
    "type": "normal",
    "subcategory": "Aeviter",
    "category": "Insectoid",
    "drops_ground_weapon": true,
    "level_range": {
      "minimum": 41,
      "maximum": 50
    },
    "experience_range": {
      "minimum": 437,
      "maximum": 604
    },
    "health_range": {
      "minimum": 74045,
      "maximum": 89595
    },
    "melee_power_range": {
      "minimum": 815,
      "maximum": 1056
    },
    "melee_accuracy_range": {
      "minimum": 208,
      "maximum": 240
    },
    "ranged_power_range": {
      "minimum": 889,
      "maximum": 1152
    },
    "ranged_accuracy_range": {
      "minimum": 243,
      "maximum": 282
    },
    "potential_range": {
      "minimum": 889,
      "maximum": 1152
    },
    "evasion_range": {
      "minimum": 118,
      "maximum": 150
    },
    "notes": "Found at 405,412,413,415,416SW(lo)",
    "time": "TBD",
    "weather": "TBD",
    "physical_resistance": 35,
    "beam_resistance": 0,
    "ether_resistance": -25,
    "thermal_resistance": -25,
    "electric_resistance": 0,
    "gravity_resistance": 0
  }
}
