{
  "id": "bayleef",
  "labels": [
    "Pokemon",
    "PokemonSeries"
  ],
  "data": {
    "species_id": 153,
    "height": 12,
    "weight": 158,
    "base_experience": 142,
    "name": "Bayleef",
    "genus": "Leaf"
  },
  "locale": {
    "ja": {
      "name": "ベイリーフ",
      "genus": "はっぱ"
    },
    "ko": {
      "name": "베이리프",
      "genus": "잎사귀"
    },
    "zh": {
      "name": "月桂葉",
      "genus": ""
    },
    "fr": {
      "name": "Macronium",
      "genus": "Feuille"
    },
    "de": {
      "name": "Lorblatt",
      "genus": "Laub"
    },
    "es": {
      "name": "Bayleef",
      "genus": "Hoja"
    },
    "it": {
      "name": "Bayleef",
      "genus": "Foglia"
    }
  }
}