{
  "id": "koffing",
  "labels": [
    "Pokemon"
  ],
  "data": {
    "species_id": 109,
    "height": 6,
    "weight": 10,
    "base_experience": 68,
    "name": "Koffing",
    "genus": "Poison Gas"
  },
  "locale": {
    "ja": {
      "name": "ドガース",
      "genus": "どくガス"
    },
    "ko": {
      "name": "또가스",
      "genus": "독가스"
    },
    "zh": {
      "name": "瓦斯彈",
      "genus": ""
    },
    "fr": {
      "name": "Smogo",
      "genus": "Gaz Mortel"
    },
    "de": {
      "name": "Smogon",
      "genus": "Giftwolke"
    },
    "es": {
      "name": "Koffing",
      "genus": "Gas Venenoso"
    },
    "it": {
      "name": "Koffing",
      "genus": "Velenuvola"
    }
  }
}
