{
  "id": "serperior",
  "labels": [
    "Pokemon"
  ],
  "data": {
    "species_id": 497,
    "height": 33,
    "weight": 630,
    "base_experience": 238,
    "name": "Serperior",
    "genus": "Regal"
  },
  "locale": {
    "ja": {
      "name": "ジャローダ",
      "genus": "ロイヤル"
    },
    "ko": {
      "name": "샤로다",
      "genus": "로열"
    },
    "fr": {
      "name": "Majaspic",
      "genus": "Majestueux"
    },
    "de": {
      "name": "Serpiroyal",
      "genus": "Hoheit"
    },
    "es": {
      "name": "Serperior",
      "genus": "Realeza"
    },
    "it": {
      "name": "Serperior",
      "genus": "Regale"
    }
  }
}
