{
  "id": "spritzee",
  "labels": [
    "Pokemon"
  ],
  "data": {
    "species_id": 682,
    "height": 2,
    "weight": 5,
    "base_experience": 68,
    "name": "Spritzee",
    "genus": "Perfume"
  },
  "locale": {
    "ja": {
      "name": "シュシュプ",
      "genus": "こうすい"
    },
    "ko": {
      "name": "슈쁘",
      "genus": "향수"
    },
    "fr": {
      "name": "Fluvetin",
      "genus": "Fragrance"
    },
    "de": {
      "name": "Parfi",
      "genus": "Parfüm"
    },
    "es": {
      "name": "Spritzee",
      "genus": "Aroma"
    },
    "it": {
      "name": "Spritzee",
      "genus": "Profumo"
    }
  }
}
