{
  "id": "macabre-gerrid",
  "labels": [
    "NormalEnemy",
    "Enemy"
  ],
  "data": {
    "name": "Macabre Gerrid",
    "subcategory": "Gerrid",
    "category": "Insectoid",
    "level_range": {
      "minimum": 31,
      "maximum": 40
    },
    "experience_range": {
      "minimum": 121,
      "maximum": 286
    },
    "health_range": {
      "minimum": 39508,
      "maximum": 55307
    },
    "melee_power_range": {
      "minimum": 384,
      "maximum": 524
    },
    "melee_accuracy_range": {
      "minimum": 195,
      "maximum": 225
    },
    "ranged_power_range": {
      "minimum": 349,
      "maximum": 477
    },
    "ranged_accuracy_range": {
      "minimum": 190,
      "maximum": 220
    },
    "potential_range": {
      "minimum": 384,
      "maximum": 524
    },
    "evasion_range": {
      "minimum": 92,
      "maximum": 120
    },
    "notes": "Found at Den of the Dead",
    "time": "TBD",
    "weather": "TBD",
    "physical_resistance": 0,
    "beam_resistance": 0,
    "ether_resistance": -25,
    "thermal_resistance": -50,
    "electric_resistance": 0,
    "gravity_resistance": 0
  }
}
