{
  "id": "farfetchd",
  "labels": [
    "Pokemon"
  ],
  "data": {
    "species_id": 83,
    "height": 8,
    "weight": 150,
    "base_experience": 123,
    "name": "Farfetch'd",
    "genus": "Wild Duck"
  },
  "locale": {
    "ja": {
      "name": "カモネギ",
      "genus": "かるがも"
    },
    "ko": {
      "name": "파오리",
      "genus": "천둥오리"
    },
    "zh": {
      "name": "大蔥鴨",
      "genus": ""
    },
    "fr": {
      "name": "Canarticho",
      "genus": "Canard Fou"
    },
    "de": {
      "name": "Porenta",
      "genus": "Wildente"
    },
    "es": {
      "name": "Farfetch'd",
      "genus": "Pato Salvaje"
    },
    "it": {
      "name": "Farfetch'd",
      "genus": "Selvanatra"
    }
  }
}
