{
  "id": "zubat",
  "labels": [
    "Pokemon"
  ],
  "data": {
    "species_id": 41,
    "height": 8,
    "weight": 75,
    "base_experience": 49,
    "name": "Zubat",
    "genus": "Bat"
  },
  "locale": {
    "ja": {
      "name": "ズバット",
      "genus": "こうもり"
    },
    "ko": {
      "name": "주뱃",
      "genus": "박쥐"
    },
    "zh": {
      "name": "超音蝠",
      "genus": ""
    },
    "fr": {
      "name": "Nosferapti",
      "genus": "Chovsouris"
    },
    "de": {
      "name": "Zubat",
      "genus": "Fledermaus"
    },
    "es": {
      "name": "Zubat",
      "genus": "Murciélago"
    },
    "it": {
      "name": "Zubat",
      "genus": "Pipistrello"
    }
  }
}
