{
  "id": "omastar",
  "labels": [
    "Pokemon",
    "PokemonSeries"
  ],
  "data": {
    "species_id": 139,
    "height": 10,
    "weight": 350,
    "base_experience": 173,
    "name": "Omastar",
    "genus": "Spiral"
  },
  "locale": {
    "ja": {
      "name": "オムスター",
      "genus": "うずまき"
    },
    "ko": {
      "name": "암스타",
      "genus": "소용돌이"
    },
    "zh": {
      "name": "多刺菊石獸",
      "genus": ""
    },
    "fr": {
      "name": "Amonistar",
      "genus": "Spirale"
    },
    "de": {
      "name": "Amoroso",
      "genus": "Spirale"
    },
    "es": {
      "name": "Omastar",
      "genus": "Espiral"
    },
    "it": {
      "name": "Omastar",
      "genus": "Spirale"
    }
  }
}